Metadata-Version: 2.4
Name: prosemirror-py-markdown
Version: 1.0.1
Summary: Python implementation of converting ProseMirror doc to markdown with TaskList support
Home-page: https://github.com/big-camel/prosemirror-py-markdown
Author: YiYang
Author-email: me@aomao.com
License: MIT
Keywords: prosemirror markdown pmconverter html python-converter tasklist task-list
Classifier: Programming Language :: Python :: 3
Classifier: License :: OSI Approved :: MIT License
Classifier: Operating System :: OS Independent
License-File: LICENSE
Dynamic: author
Dynamic: author-email
Dynamic: classifier
Dynamic: description
Dynamic: description-content-type
Dynamic: home-page
Dynamic: keywords
Dynamic: license
Dynamic: license-file
Dynamic: summary
